localecmddoc/__init__.py
localecmddoc/autodoc.py
localecmddoc/codeblock.py
localecmddoc/py.typed
sphinx_localecmddoc-0.5.2.dist-info/METADATA
sphinx_localecmddoc-0.5.2.dist-info/WHEEL
sphinx_localecmddoc-0.5.2.dist-info/licenses/LICENSE
sphinx_localecmddoc-0.5.2.dist-info/RECORD
