Metadata-Version: 2.4
Name: sphinx_localecmddoc
Version: 0.5.2
Summary: Sphinx extension for autodocumenting localecmd modules
Project-URL: Documentation, https://codeberg.org/jbox/sphinx_localecmddoc
Project-URL: Issues, https://codeberg.org/jbox/sphinx_localecmddoc/issues
Project-URL: Source, https://codeberg.org/jbox/sphinx_localecmddoc
Author-email: j-box <j-box@blueline.email>
License-Expression: BSD-3-Clause
License-File: LICENSE
Classifier: Development Status :: 4 - Beta
Classifier: Framework :: Sphinx :: Extension
Classifier: Programming Language :: Python
Classifier: Programming Language :: Python :: 3
Classifier: Programming Language :: Python :: Implementation :: CPython
Classifier: Programming Language :: Python :: Implementation :: PyPy
Classifier: Topic :: Documentation :: Sphinx
Requires-Python: >=3.8
Requires-Dist: jinja2
Requires-Dist: localecmd
Requires-Dist: myst-parser
Requires-Dist: sphinx
